scarches/__init__.py
scarches/classifiers/__init__.py
scarches/dataset/__init__.py
scarches/dataset/DHH_data/_DHH_data.py
scarches/dataset/DHH_data/__init__.py
scarches/dataset/MGA_data/_MGA_data.py
scarches/dataset/MGA_data/__init__.py
scarches/dataset/scpoli/__init__.py
scarches/dataset/scpoli/_utils.py
scarches/dataset/scpoli/anndata.py
scarches/dataset/trvae/__init__.py
scarches/dataset/trvae/_utils.py
scarches/dataset/trvae/anndata.py
scarches/dataset/trvae/data_handling.py
scarches/metrics/__init__.py
scarches/metrics/clustering.py
scarches/metrics/metrics.py
scarches/models/__init__.py
scarches/models/base/__init__.py
scarches/models/base/_base.py
scarches/models/base/_utils.py
scarches/models/expimap/__init__.py
scarches/models/expimap/expimap.py
scarches/models/expimap/expimap_model.py
scarches/models/expimap/losses.py
scarches/models/expimap/modules.py
scarches/models/sagenet/__init__.py
scarches/models/sagenet/classifier.py
scarches/models/sagenet/model.py
scarches/models/sagenet/sagenet.py
scarches/models/sagenet/utils.py
scarches/models/scgen/__init__.py
scarches/models/scgen/_utils.py
scarches/models/scgen/modules.py
scarches/models/scgen/vaearith.py
scarches/models/scgen/vaearith_model.py
scarches/models/scpoli/__init__.py
scarches/models/scpoli/_utils.py
scarches/models/scpoli/scpoli.py
scarches/models/scpoli/scpoli_model.py
scarches/models/trvae/__init__.py
scarches/models/trvae/_utils.py
scarches/models/trvae/adaptors.py
scarches/models/trvae/losses.py
scarches/models/trvae/modules.py
scarches/models/trvae/trvae.py
scarches/models/trvae/trvae_model.py
scarches/plotting/__init__.py
scarches/plotting/_alluvial.py
scarches/plotting/sankey.py
scarches/plotting/scvi_eval.py
scarches/plotting/terms_scores.py
scarches/plotting/trvae_eval.py
scarches/surgery/__init__.py
scarches/surgery/trvae.py
scarches/trainers/__init__.py
scarches/trainers/expimap/__init__.py
scarches/trainers/expimap/regularized.py
scarches/trainers/scgen/__init__.py
scArches-0.6.1.dist-info/LICENSE
scArches-0.6.1.dist-info/METADATA
scArches-0.6.1.dist-info/WHEEL
scArches-0.6.1.dist-info/top_level.txt
scArches-0.6.1.dist-info/RECORD
