Metadata-Version: 2.1
Name: scArches
Version: 0.6.1
Summary: Transfer learning with Architecture Surgery on Single-cell data
Home-page: https://github.com/theislab/scarches
Author: 
Author-email: 
License: MIT
Classifier: Programming Language :: Python :: 3.9
Classifier: Environment :: Console
Classifier: Framework :: Jupyter
Classifier: Intended Audience :: Developers
Classifier: Intended Audience :: Science/Research
Classifier: License :: OSI Approved :: MIT License
Classifier: Natural Language :: English
Classifier: Operating System :: MacOS :: MacOS X
Classifier: Operating System :: Microsoft :: Windows
Classifier: Operating System :: POSIX :: Linux
License-File: LICENSE
Requires-Dist: scanpy >=1.6.0
Requires-Dist: anndata >=0.7.4
Requires-Dist: scHPL >=1.0.0
Requires-Dist: h5py >=2.10.0
Requires-Dist: torch >=1.8.0
Requires-Dist: numpy >=1.19.2
Requires-Dist: scipy >=1.5.2
Requires-Dist: scikit-learn >=0.23.2
Requires-Dist: matplotlib >=3.3.1
Requires-Dist: pandas >=1.1.2
Requires-Dist: scvi-tools >=0.12.1
Requires-Dist: tqdm >=4.56.0
Requires-Dist: requests
Requires-Dist: gdown
Requires-Dist: leidenalg
Requires-Dist: muon
